jokyt/__init__.py
jokyt-1.0.dist-info/METADATA
jokyt-1.0.dist-info/WHEEL
jokyt-1.0.dist-info/top_level.txt
jokyt-1.0.dist-info/RECORD
