Metadata-Version: 2.4
Name: jokyt
Version: 1.0
Summary: Simple YouTube cookie injector for yt_dlp
Home-page: https://pypi.org/project/jokyt/
Author: Hussein Ali
Author-email: hh0000ss28@gmail.com
Classifier: Programming Language :: Python :: 3
Classifier: License :: OSI Approved :: MIT License
Requires-Python: >=3.10
Dynamic: author
Dynamic: author-email
Dynamic: classifier
Dynamic: home-page
Dynamic: requires-python
Dynamic: summary
